avirtech_route_drone_filter/__init__.py
avirtech_route_drone_filter/route_drone_filter.py
avirtech_route_drone_filter-0.0.3.dist-info/METADATA
avirtech_route_drone_filter-0.0.3.dist-info/WHEEL
avirtech_route_drone_filter-0.0.3.dist-info/top_level.txt
avirtech_route_drone_filter-0.0.3.dist-info/RECORD
